pyCapsid/CG.py
pyCapsid/NMA.py
pyCapsid/PDB.py
pyCapsid/QRC.py
pyCapsid/VIS.py
pyCapsid/__init__.py
pyCapsid/bfactorfit.py
pyCapsid/clustering_util.py
pyCapsid/scripts/__init__.py
pyCapsid/scripts/chimerax_script.py
pyCapsid/scripts/chimerax_script_animate_mode.py
pyCapsid/scripts/chimerax_script_colab.py
pycapsid-0.6.1.dist-info/licenses/LICENSE.txt
pycapsid-0.6.1.dist-info/METADATA
pycapsid-0.6.1.dist-info/WHEEL
pycapsid-0.6.1.dist-info/top_level.txt
pycapsid-0.6.1.dist-info/RECORD
